symsearch/__init__.py
symsearch/asym_args.py
symsearch/inference.py
symsearch/rerank/__init__.py
symsearch/rerank/modeling.py
symsearch/retrieve/__init__.py
symsearch/retrieve/baseline.py
symsearch/retrieve/modeling.py
symsearch-0.0.2.dist-info/LICENSE
symsearch-0.0.2.dist-info/METADATA
symsearch-0.0.2.dist-info/WHEEL
symsearch-0.0.2.dist-info/top_level.txt
symsearch-0.0.2.dist-info/RECORD
