Metadata-Version: 2.1
Name: symsearch
Version: 0.0.2
Summary: symsearch is a search engine for research and development that uses a searching and ranking pipeline in Dense Passage Retrieval.
Home-page: https://github.com/tien-ngnvan/symsearch
Author: tien-ngnvan
Author-email: tien.ngnvan@gmail.com
Maintainer: Tien Nguyen Van
Maintainer-email: tien.ngnvan@gmail.com
Requires-Python: >=3.8
License-File: LICENSE
Requires-Dist: transformers
